odoo9_addon_purchase_open_qty-9.0.1.0.1-py2.7-nspkg.pth
odoo9_addon_purchase_open_qty-9.0.1.0.1.dist-info/DESCRIPTION.rst
odoo9_addon_purchase_open_qty-9.0.1.0.1.dist-info/METADATA
odoo9_addon_purchase_open_qty-9.0.1.0.1.dist-info/RECORD
odoo9_addon_purchase_open_qty-9.0.1.0.1.dist-info/WHEEL
odoo9_addon_purchase_open_qty-9.0.1.0.1.dist-info/metadata.json
odoo9_addon_purchase_open_qty-9.0.1.0.1.dist-info/namespace_packages.txt
odoo9_addon_purchase_open_qty-9.0.1.0.1.dist-info/top_level.txt
odoo_addons/purchase_open_qty/README.rst
odoo_addons/purchase_open_qty/__init__.py
odoo_addons/purchase_open_qty/__openerp__.py
odoo_addons/purchase_open_qty/init_hook.py
odoo_addons/purchase_open_qty/i18n/de.po
odoo_addons/purchase_open_qty/i18n/es.po
odoo_addons/purchase_open_qty/i18n/es_MX.po
odoo_addons/purchase_open_qty/i18n/fi.po
odoo_addons/purchase_open_qty/i18n/fr.po
odoo_addons/purchase_open_qty/i18n/fr_FR.po
odoo_addons/purchase_open_qty/i18n/gl.po
odoo_addons/purchase_open_qty/i18n/it.po
odoo_addons/purchase_open_qty/i18n/nl.po
odoo_addons/purchase_open_qty/i18n/pt_BR.po
odoo_addons/purchase_open_qty/i18n/pt_PT.po
odoo_addons/purchase_open_qty/i18n/ro.po
odoo_addons/purchase_open_qty/i18n/sl.po
odoo_addons/purchase_open_qty/i18n/vi_VN.po
odoo_addons/purchase_open_qty/models/__init__.py
odoo_addons/purchase_open_qty/models/purchase_order.py
odoo_addons/purchase_open_qty/static/description/icon.png
odoo_addons/purchase_open_qty/tests/__init__.py
odoo_addons/purchase_open_qty/tests/test_purchase_open_qty.py
odoo_addons/purchase_open_qty/views/purchase_view.xml
