Metadata-Version: 2.0
Name: odoo9-addon-purchase-open-qty
Version: 9.0.1.0.1
Summary: Allows to identify the purchase orders that have quantities pending to invoice or to receive.
Home-page: https://github.com/OCA/purchase-workflow
Author: Eficent, Odoo Community Association (OCA)
Author-email: support@odoo-community.org
License: AGPL-3
Platform: UNKNOWN
Classifier: Programming Language :: Python :: 2.7
Classifier: Framework :: Odoo
Classifier: License :: OSI Approved :: GNU Affero General Public License v3
Requires-Dist: odoo (<9.1a,>=9.0a)
